trtools/__init__.py
trtools/annotaTR/__init__.py
trtools/annotaTR/annotaTR.py
trtools/annotaTR/tests/__init__.py
trtools/annotaTR/tests/test_annotaTR.py
trtools/associaTR/__init__.py
trtools/associaTR/associaTR.py
trtools/associaTR/load_and_filter_genotypes.py
trtools/associaTR/tests/__init__.py
trtools/associaTR/tests/test_associaTR.py
trtools/compareSTR/__init__.py
trtools/compareSTR/compareSTR.py
trtools/compareSTR/tests/__init__.py
trtools/compareSTR/tests/test_compareSTR.py
trtools/dumpSTR/__init__.py
trtools/dumpSTR/dumpSTR.py
trtools/dumpSTR/filters.py
trtools/dumpSTR/tests/__init__.py
trtools/dumpSTR/tests/test_dumpSTR.py
trtools/dumpSTR/tests/test_filters.py
trtools/mergeSTR/__init__.py
trtools/mergeSTR/mergeSTR.py
trtools/mergeSTR/tests/__init__.py
trtools/mergeSTR/tests/test_mergeSTR.py
trtools/prancSTR/__init__.py
trtools/prancSTR/prancSTR.py
trtools/prancSTR/tests/__init__.py
trtools/prancSTR/tests/test_prancSTR.py
trtools/qcSTR/__init__.py
trtools/qcSTR/qcSTR.py
trtools/qcSTR/tests/.bandit
trtools/qcSTR/tests/__init__.py
trtools/qcSTR/tests/test_qcSTR.py
trtools/simTR/__init__.py
trtools/simTR/simTR.py
trtools/simTR/tests/__init__.py
trtools/simTR/tests/test_simTR.py
trtools/statSTR/__init__.py
trtools/statSTR/statSTR.py
trtools/statSTR/tests/__init__.py
trtools/statSTR/tests/test_statSTR.py
trtools/utils/__init__.py
trtools/utils/common.py
trtools/utils/mergeutils.py
trtools/utils/tests/.bandit
trtools/utils/tests/__init__.py
trtools/utils/tests/test_common.py
trtools/utils/tests/test_mergeutils.py
trtools/utils/tests/test_trharmonizer.py
trtools/utils/tests/test_utils.py
trtools/utils/tr_harmonizer.py
trtools/utils/utils.py
trtools-6.1.0.data/scripts/test_trtools.sh
trtools-6.1.0.data/scripts/trtools_prep_beagle_vcf.sh
trtools-6.1.0.dist-info/LICENSE.txt
trtools-6.1.0.dist-info/METADATA
trtools-6.1.0.dist-info/WHEEL
trtools-6.1.0.dist-info/entry_points.txt
trtools-6.1.0.dist-info/RECORD
